Workbook

Sheet README
A1: Splitwise Alternative — DB Schema (with dummy data)
A4: Purpose | B4: A walkthrough of every table in the schema with realistic dummy data so you can see how the entities connect.
A5: DB Engine | B5: PostgreSQL 16 (recommended). All money columns use NUMERIC(14,2). All ids are UUIDs (shortened here for readability, e.g. u001).
A6: Source of truth | B6: ledger_entries. Balances are NEVER computed from expenses directly. Every expense + settlement writes balanced ledger entries.
A7: Soft delete | B7: Most tables use deleted_at TIMESTAMPTZ instead of hard delete. Audit log keeps the truth.
A8: Idempotency | B8: settlements has idempotency_key UNIQUE — prevents double-debit on payment webhook retries.
A10: READING ORDER | B10: The sheets are arranged in the order you should read them to understand the model.
A11: 1. users | B11: People. Includes ghost users (placeholder for not-yet-signed-up friends).
A12: 2. devices | B12: Push tokens per user.
A13: 3. friendships | B13: 1-on-1 relationships outside groups.
A14: 4. groups | B14: Trip / Home / Couple etc.
A15: 5. group_members | B15: M:N between users and groups.
A16: 6. categories | B16: Food, Rent, Transport… plus user-custom categories.
... A34: 24. ★ workflow_example | B34: Step-by-step walk through what happens when an expense is added & settled.
A36: Color coding in this file
A37: Header (dark blue) | B37: Column names — exactly what would be in the SQL DDL.
A38: Notes (italic grey) | B38: Extra context for that table — purpose, indexes, gotchas.
A39: ★ | B39: Sheets that demonstrate the model in action (formulas + walkthrough).
B42: How they connect (mental model)
B44: users ──< group_members >── groups
B45: │ │
B46: │ └──< expenses >── expense_payers
B47: │ │ │
B48: │ ├──< expense_splits
B49: │ ├──< expense_items >── expense_item_assignments
B50: │ └──< receipts (OCR'd)
B51: │
B52: ├──< ledger_entries (every expense + settlement writes here) — SOURCE OF TRUTH for balances
B53: │
B54: ├──< settlements ──< (writes ledger_entries when status=success)
... B89: audit_log row 3 shows Priya edited the dinner description from "Beach Dinner" → "Beachside Dinner". That history is permanent and visible to all group members.

Sheet users
A1: users
A2: People in the system. Ghost users (is_ghost=true) are placeholders so you can add expenses for friends who haven't signed up yet. They get converted when they accept the invite.
A4: id | B4: phone | C4: email | D4: name | E4: photo_url | F4: default_currency | G4: vpa | H4: language | I4: kyc_tier | J4: is_ghost | K4: created_at | L4: updated_at | M4: deleted_at
A5: u001 | B5: +919812340001 | C5: aarav@example.com | D5: Aarav Sharma | E5: s3://photos/u001.jpg | F5: INR | G5: aarav@oksbi | H5: en | I5: 1 | J5: =FALSE() -> FALSE | K5: 2026-01-15 10:30:00 | L5: 2026-04-20 12:00:00
A6: u002 | B6: +919812340002 | C6: priya@example.com | D6: Priya Verma | E6: s3://photos/u002.jpg | F6: INR | G6: priya@okhdfcbank | H6: hi | I6: 1 | J6: =FALSE() -> FALSE | K6: 2026-01-20 14:15:00 | L6: 2026-04-22 09:00:00
A7: u003 | B7: +919812340003 | C7: rohan@example.com | D7: Rohan Mehta | F7: INR | G7: rohan@okicici | H7: en | I7: 0 | J7: =FALSE() -> FALSE | K7: 2026-02-01 18:45:00 | L7: 2026-04-25 20:30:00
A8: u004 | B8: +919812340004 | C8: neha@example.com | D8: Neha Kapoor | E8: s3://photos/u004.jpg | F8: INR | G8: neha@oksbi | H8: en | I8: 1 | J8: =FALSE() -> FALSE | K8: 2026-02-10 11:20:00 | L8: 2026-04-26 16:00:00
A9: u005 | B9: +919812340005 | C9: karan@example.com | D9: Karan Iyer | E9: s3://photos/u005.jpg | F9: INR | G9: karan.iyer@okaxis | H9: ta | I9: 1 | J9: =FALSE() -> FALSE | K9: 2026-02-15 09:00:00 | L9: 2026-04-27 14:30:00
A10: u006 | D10: Vikram (ghost) | F10: INR | H10: en | I10: 0 | J10: =TRUE() -> TRUE | K10: 2026-04-10 19:00:00 | L10: 2026-04-10 19:00:00

Sheet devices
A1: devices
A2: Push notification tokens per user per device. A user can have multiple devices.
A4: id | B4: user_id | C4: fcm_token | D4: platform | E4: app_version | F4: last_active_at
A5: d001 | B5: u001 | C5: fcm_AAA111... | D5: android | E5: 1.0.0 | F5: 2026-04-28 09:30:00
A6: d002 | B6: u001 | C6: apns_AAA222... | D6: ios | E6: 1.0.0 | F6: 2026-04-28 08:00:00
A7: d003 | B7: u002 | C7: fcm_BBB333... | D7: android | E7: 1.0.0 | F7: 2026-04-28 10:15:00
A8: d004 | B8: u003 | C8: fcm_CCC444... | D8: android | E8: 1.0.0 | F8: 2026-04-27 22:00:00
A9: d005 | B9: u004 | C9: apns_DDD555... | D9: ios | E9: 1.0.0 | F9: 2026-04-28 07:45:00
A10: d006 | B10: u005 | C10: fcm_EEE666... | D10: android | E10: 1.0.0 | F10: 2026-04-28 11:00:00

Sheet friendships
A1: friendships
A2: 1-on-1 friendships outside groups. Convention: user_a_id < user_b_id (alphabetical) to avoid duplicate pairs.
A4: user_a_id | B4: user_b_id | C4: created_at
A5: u001 | B5: u002 | C5: 2026-01-21 10:00:00
A6: u001 | B6: u003 | C6: 2026-02-01 19:00:00
A7: u001 | B7: u004 | C7: 2026-02-10 12:00:00
A8: u001 | B8: u005 | C8: 2026-02-15 10:00:00
A9: u002 | B9: u004 | C9: 2026-02-12 15:00:00
A10: u003 | B10: u005 | C10: 2026-02-16 11:00:00

Sheet groups
A1: groups
A2: Trip / Home / Couple / Wedding / Custom. simplify_debts=false on couples (they prefer raw who-paid-what).
A4: id | B4: name | C4: type | D4: default_currency | E4: simplify_debts | F4: archived_at | G4: created_by | H4: created_at | I4: updated_at
A5: g001 | B5: Bangalore Flat | C5: home | D5: INR | E5: =TRUE() -> TRUE | G5: u001 | H5: 2026-02-01 19:30:00 | I5: 2026-04-01 10:00:00
A6: g002 | B6: Goa Trip Apr 2026 | C6: trip | D6: INR | E6: =TRUE() -> TRUE | G6: u001 | H6: 2026-04-05 20:00:00 | I6: 2026-04-25 18:00:00
A7: g003 | B7: Aarav & Priya | C7: couple | D7: INR | E7: =FALSE() -> FALSE | G7: u001 | H7: 2026-01-22 11:00:00 | I7: 2026-04-26 14:00:00

Sheet group_members
A1: group_members
A2: M:N table linking users to groups. Includes ghost users (u006 in Goa trip).
A4: group_id | B4: user_id | C4: role | D4: joined_at | E4: left_at
A5: g001 | B5: u001 | C5: owner | D5: 2026-02-01 19:30:00
A6: g001 | B6: u003 | C6: member | D6: 2026-02-01 19:35:00
A7: g001 | B7: u005 | C7: member | D7: 2026-02-01 19:40:00
A8: g002 | B8: u001 | C8: owner | D8: 2026-04-05 20:00:00
A9: g002 | B9: u002 | C9: member | D9: 2026-04-05 20:05:00
A10: g002 | B10: u003 | C10: member | D10: 2026-04-05 20:06:00
A11: g002 | B11: u004 | C11: member | D11: 2026-04-05 20:07:00
A12: g002 | B12: u006 | C12: member | D12: 2026-04-10 19:00:00
A13: g003 | B13: u001 | C13: owner | D13: 2026-01-22 11:00:00
A14: g003 | B14: u002 | C14: member | D14: 2026-01-22 11:01:00

Sheet categories
A1: categories
A2: 30+ system categories shipped (is_system=true). Users can create custom categories on free tier (is_system=false, user_id set).
A4: id | B4: name | C4: icon | D4: color | E4: parent_id | F4: is_system | G4: user_id
A5: c001 | B5: Food & Drink | C5: 🍔 | D5: #FF6B35 | F5: =TRUE() -> TRUE
A6: c002 | B6: Rent | C6: 🏠 | D6: #4A90E2 | F6: =TRUE() -> TRUE
A7: c003 | B7: Transportation | C7: 🚗 | D7: #7ED321 | F7: =TRUE() -> TRUE
A8: c004 | B8: Entertainment | C8: 🎬 | D8: #BD10E0 | F8: =TRUE() -> TRUE
A9: c005 | B9: Utilities | C9: 💡 | D9: #F5A623 | F9: =TRUE() -> TRUE
A10: c006 | B10: Restaurants | C10: 🍽️ | D10: #FF6B35 | E10: c001 | F10: =TRUE() -> TRUE
A11: c007 | B11: Flights | C11: ✈️ | D11: #7ED321 | E11: c003 | F11: =TRUE() -> TRUE
A12: c008 | B12: Diwali Pooling | C12: 🪔 | D12: #E94B3C | F12: =FALSE() -> FALSE | G12: u002

Sheet expenses
A1: expenses
A2: Main expense table. group_id NULL for 1-on-1 non-group expenses. fx_rate_to_base snapshotted at entry time so historical balances stay correct even if rates change.
A4: id | B4: group_id | C4: description | D4: amount | E4: currency | F4: fx_rate_to_base | G4: spent_at | H4: category_id | I4: notes | J4: receipt_id | K4: created_by | L4: created_at | M4: updated_at | N4: deleted_at
A5: e001 | B5: g001 | C5: April Rent | D5: 45000 | E5: INR | F5: 1 | G5: 2026-04-01 | H5: c002 | I5: Includes maintenance | K5: u001 | L5: 2026-04-01 09:30:00 | M5: 2026-04-01 09:30:00
A6: e002 | B6: g002 | C6: Beachside Dinner | D6: 4500 | E6: INR | F6: 1 | G6: 2026-04-15 | H6: c006 | I6: Curlies shack — split by item | J6: r001 | K6: u002 | L6: 2026-04-15 22:30:00 | M6: 2026-04-15 22:35:00
A7: e003 | B7: g002 | C7: Flight tickets BLR-GOI | D7: 20000 | E7: INR | F7: 1 | G7: 2026-04-12 | H7: c007 | I7: Indigo, return tickets — 2 payers | K7: u001 | L7: 2026-04-12 14:00:00 | M7: 2026-04-12 14:00:00
A8: e004 | B8: g003 | C8: Coffee at Third Wave | D8: 400 | E8: INR | F8: 1 | G8: 2026-04-26 | H8: c001 | K8: u001 | L8: 2026-04-26 16:00:00 | M8: 2026-04-26 16:00:00

Sheet expense_payers
A1: expense_payers
A2: Who actually paid. Sum per expense_id MUST equal expenses.amount. e003 demonstrates multi-payer (Aarav paid 15k, Neha paid 5k, total 20k).
A4: expense_id | B4: user_id | C4: amount_paid
A5: e001 | B5: u001 | C5: 45000
A6: e002 | B6: u002 | C6: 4500
A7: e003 | B7: u001 | C7: 15000
A8: e003 | B8: u004 | C8: 5000
A9: e004 | B9: u001 | C9: 400

Sheet expense_splits
A1: expense_splits
A2: Who owes what share. Sum per expense_id = expenses.amount. share_value is the raw input (e.g. 25 for percent, 2 for shares). For equal/item splits it's 1.0/null.
A4: expense_id | B4: user_id | C4: share_amount | D4: split_type | E4: share_value
A5: e001 | B5: u001 | C5: 15000 | D5: equal | E5: 1
A6: e001 | B6: u003 | C6: 15000 | D6: equal | E6: 1
A7: e001 | B7: u005 | C7: 15000 | D7: equal | E7: 1
A8: e002 | B8: u001 | C8: 900 | D8: item
A9: e002 | B9: u002 | C9: 900 | D9: item
A10: e002 | B10: u003 | C10: 900 | D10: item
A11: e002 | B11: u004 | C11: 900 | D11: item
A12: e002 | B12: u006 | C12: 900 | D12: item
A13: e003 | B13: u001 | C13: 5000 | D13: equal | E13: 1
A14: e003 | B14: u002 | C14: 5000 | D14: equal | E14: 1
A15: e003 | B15: u003 | C15: 5000 | D15: equal | E15: 1
A16: e003 | B16: u004 | C16: 5000 | D16: equal | E16: 1
A17: e004 | B17: u001 | C17: 200 | D17: equal | E17: 1
A18: e004 | B18: u002 | C18: 200 | D18: equal | E18: 1

Sheet expense_items
A1: expense_items
A2: Optional — only used when split_type=item. Total of items = expense amount (1600 + 1200 + 1400 + 300 = 4500 ✓).
A4: id | B4: expense_id | C4: description | D4: amount | E4: qty
A5: i001 | B5: e002 | C5: Fish curry | D5: 800 | E5: 2
A6: i002 | B6: e002 | C6: Prawns masala | D6: 1200 | E6: 1
A7: i003 | B7: e002 | C7: Beer (pint) | D7: 350 | E7: 4
A8: i004 | B8: e002 | C8: Tax & service | D8: 300 | E8: 1

Sheet expense_item_assignments
A1: expense_item_assignments
A2: Who claims which item (and how much of it). qty_share allows partial claims. Final share_amount in expense_splits is computed from this.
A4: item_id | B4: user_id | C4: qty_share
A5: i001 | B5: u001 | C5: 1
A6: i001 | B6: u003 | C6: 1
A7: i002 | B7: u002 | C7: 0.5
A8: i002 | B8: u004 | C8: 0.5
A9: i003 | B9: u001 | C9: 1
A10: i003 | B10: u003 | C10: 2
A11: i003 | B11: u006 | C11: 1
A12: i004 | B12: u001 | C12: 0.2
A13: i004 | B13: u002 | C13: 0.2
A14: i004 | B14: u003 | C14: 0.2
A15: i004 | B15: u004 | C15: 0.2
A16: i004 | B16: u006 | C16: 0.2

Sheet ledger_entries
A1: ledger_entries
A2: ★ THE SOURCE OF TRUTH. Append-only, never updated. debit_user_id is owed amount FROM credit_user_id. Settlement le010 reverses the original debt (Aarav→Rohan) by writing the opposite direction (Rohan→Aarav).
A4: id | B4: txn_id | C4: source_type | D4: source_id | E4: group_id | F4: debit_user_id | G4: credit_user_id | H4: amount | I4: currency | J4: fx_rate_to_base | K4: created_at
A5: le001 | B5: txn001 | C5: expense | D5: e001 | E5: g001 | F5: u001 | G5: u003 | H5: 15000 | I5: INR | J5: 1 | K5: 2026-04-01 09:30:00
A6: le002 | B6: txn001 | C6: expense | D6: e001 | E6: g001 | F6: u001 | G6: u005 | H6: 15000 | I6: INR | J6: 1 | K6: 2026-04-01 09:30:00
A7: le003 | B7: txn002 | C7: expense | D7: e002 | E7: g002 | F7: u002 | G7: u001 | H7: 900 | I7: INR | J7: 1 | K7: 2026-04-15 22:30:00
A8: le004 | B8: txn002 | C8: expense | D8: e002 | E8: g002 | F8: u002 | G8: u003 | H8: 900 | I8: INR | J8: 1 | K8: 2026-04-15 22:30:00
A9: le005 | B9: txn002 | C9: expense | D9: e002 | E9: g002 | F9: u002 | G9: u004 | H9: 900 | I9: INR | J9: 1 | K9: 2026-04-15 22:30:00
A10: le006 | B10: txn002 | C10: expense | D10: e002 | E10: g002 | F10: u002 | G10: u006 | H10: 900 | I10: INR | J10: 1 | K10: 2026-04-15 22:30:00
A11: le007 | B11: txn003 | C11: expense | D11: e003 | E11: g002 | F11: u001 | G11: u002 | H11: 5000 | I11: INR | J11: 1 | K11: 2026-04-12 14:00:00
A12: le008 | B12: txn003 | C12: expense | D12: e003 | E12: g002 | F12: u001 | G12: u003 | H12: 5000 | I12: INR | J12: 1 | K12: 2026-04-12 14:00:00
A13: le009 | B13: txn004 | C13: expense | D13: e004 | E13: g003 | F13: u001 | G13: u002 | H13: 200 | I13: INR | J13: 1 | K13: 2026-04-26 16:00:00
A14: le010 | B14: txn005 | C14: settlement | D14: s001 | E14: g001 | F14: u003 | G14: u001 | H14: 15000 | I14: INR | J14: 1 | K14: 2026-04-27 11:00:00

Sheet settlements
A1: settlements
A2: Status flow: pending → success (writes ledger entries) OR failed/reversed. idempotency_key UNIQUE prevents double-processing on webhook retries. s002 is pending — no ledger entries written until success.
A4: id | B4: payer_id | C4: payee_id | D4: group_id | E4: amount | F4: currency | G4: method | H4: pa_provider | I4: pa_txn_id | J4: idempotency_key | K4: status | L4: initiated_at | M4: settled_at | N4: metadata
A5: s001 | B5: u003 | C5: u001 | D5: g001 | E5: 15000 | F5: INR | G5: upi_deeplink | I5: UPI/426712345678 | J5: idem_8a3f9b2c | K5: success | L5: 2026-04-27 10:55:00 | M5: 2026-04-27 11:00:00 | N5: {"upi_app":"gpay"}
A6: s002 | B6: u005 | C6: u001 | D6: g001 | E6: 5000 | F6: INR | G6: upi_collect | H6: razorpay | I6: rzp_ord_NX23kf | J6: idem_7b2e1d4a | K6: pending | L6: 2026-04-28 09:00:00 | N6: {"collect_request_id":"crq_ABC123"}

Sheet receipts
A1: receipts
A2: Receipt photo + OCR result stored in ocr_data jsonb. expense_id can be NULL if uploaded before the expense is saved (then linked on save).
A4: id | B4: expense_id | C4: s3_key | D4: mime_type | E4: size_bytes | F4: ocr_status | G4: ocr_provider | H4: ocr_data | I4: created_by | J4: created_at
A5: r001 | B5: e002 | C5: receipts/2026/04/r001.jpg | D5: image/jpeg | E5: 1245678 | F5: done | G5: mindee | H5: {"vendor":"Curlies Shack","total":4500,"tax":300,"items":[{"name":"Fish curry","qty":2,"price":800},{"name":"Prawns masala","qty":1,"price":1200},{"name":"Beer","qty":4,"price":350}]} | I5: u002 | J5: 2026-04-15 22:28:00

Sheet chat_messages
A1: chat_messages
A2: In-app chat. expense_ref_id anchors a message to a specific expense (the "reply to expense" thread). reactions stored as jsonb {emoji: [user_ids]}.
A4: id | B4: group_id | C4: sender_id | D4: body | E4: reply_to_id | F4: attachment_url | G4: expense_ref_id | H4: reactions | I4: created_at | J4: edited_at | K4: deleted_at
A5: m001 | B5: g001 | C5: u001 | D5: Paid the April rent guys | G5: e001 | H5: {"👍":["u003","u005"]} | I5: 2026-04-01 09:31:00
A6: m002 | B6: g001 | C6: u003 | D6: Settling now via GPay 🙏 | E6: m001 | H6: {} | I6: 2026-04-01 09:35:00
A7: m003 | B7: g002 | C7: u002 | D7: Dinner was incredible 🐟 | G7: e002 | H7: {"❤️":["u001","u003","u004"]} | I7: 2026-04-15 22:40:00
A8: m004 | B8: g002 | C8: u001 | D8: Ghost member Vikram still owes 900 😅 | H8: {} | I8: 2026-04-16 10:00:00

Sheet comments
A1: comments
A2: Threaded comments on expenses (or settlements). Distinct from chat_messages — these are anchored, focused discussions.
A4: id | B4: target_type | C4: target_id | D4: user_id | E4: body | F4: created_at
A5: cm001 | B5: expense | C5: e003 | D5: u002 | E5: Why did this cost so much? Peak season? | F5: 2026-04-12 15:00:00
A6: cm002 | B6: expense | C6: e003 | D6: u001 | E6: Yeah, last-minute booking unfortunately | F6: 2026-04-12 15:05:00

Sheet notifications
A1: notifications
A2: Outbox for push/email/in-app. payload is jsonb with all data needed to render the notification (no joins needed at send time).
A4: id | B4: user_id | C4: type | D4: payload | E4: read_at | F4: created_at
A5: n001 | B5: u003 | C5: new_expense | D5: {"expense_id":"e001","group":"Bangalore Flat","amount":15000,"description":"April Rent"} | E5: 2026-04-01 10:00:00 | F5: 2026-04-01 09:30:30
A6: n002 | B6: u005 | C6: new_expense | D6: {"expense_id":"e001","group":"Bangalore Flat","amount":15000,"description":"April Rent"} | F6: 2026-04-01 09:30:30
A7: n003 | B7: u001 | C7: settlement_received | D7: {"settlement_id":"s001","payer":"Rohan","amount":15000} | E7: 2026-04-27 11:01:00 | F7: 2026-04-27 11:00:30
A8: n004 | B8: u005 | C8: reminder | D8: {"group":"Bangalore Flat","you_owe":15000,"to":"Aarav"} | F8: 2026-04-27 09:00:00

Sheet audit_log
A1: audit_log
A2: Immutable history. Visible to all group members (per FR-AUD-01). Drives the "edited X minutes ago" UI and dispute investigations.
A4: id | B4: actor_id | C4: entity_type | D4: entity_id | E4: action | F4: before | G4: after | H4: created_at
A5: 1 | B5: u001 | C5: expense | D5: e001 | E5: create | G5: {"description":"April Rent","amount":45000} | H5: 2026-04-01 09:30:00
A6: 2 | B6: u002 | C6: expense | D6: e002 | E6: create | G6: {"description":"Beach Dinner","amount":4500} | H6: 2026-04-15 22:30:00
A7: 3 | B7: u002 | C7: expense | D7: e002 | E7: update | F7: {"description":"Beach Dinner"} | G7: {"description":"Beachside Dinner"} | H7: 2026-04-15 22:35:00
A8: 4 | B8: u003 | C8: settlement | D8: s001 | E8: create | G8: {"amount":15000,"method":"upi_deeplink"} | H8: 2026-04-27 10:55:00

Sheet fx_rates
A1: fx_rates
A2: Daily snapshot from Open Exchange Rates. PK = (base, quote, fetched_at::date). Expense rows snapshot fx_rate_to_base at write time so they're immune to future rate changes.
A4: base | B4: quote | C4: rate | D4: fetched_at
A5: INR | B5: USD | C5: 0.012 | D5: 2026-04-28 06:00:00
A6: USD | B6: INR | C6: 83.45 | D6: 2026-04-28 06:00:00
A7: INR | B7: EUR | C7: 0.011 | D7: 2026-04-28 06:00:00
A8: EUR | B8: INR | C8: 90.2 | D8: 2026-04-28 06:00:00
A9: INR | B9: GBP | C9: 0.0095 | D9: 2026-04-28 06:00:00
A10: GBP | B10: INR | C10: 105.3 | D10: 2026-04-28 06:00:00

Sheet recurring_expenses
A1: recurring_expenses
A2: Cron-scheduled. Worker reads next_run_at, materializes template_payload into a real expense row, advances next_run_at. Pause = set active=false.
A4: id | B4: group_id | C4: template_payload | D4: schedule_cron | E4: next_run_at | F4: active | G4: created_by
A5: re001 | B5: g001 | C5: {"description":"Monthly Rent","amount":45000,"category_id":"c002","payers":[{"user_id":"u001","amount":45000}],"split":{"type":"equal","users":["u001","u003","u005"]}} | D5: 0 9 1 * * | E5: 2026-05-01 09:00:00 | F5: =TRUE() -> TRUE | G5: u001
A6: re002 | B6: g001 | C6: {"description":"Netflix","amount":499,"category_id":"c004","payers":[{"user_id":"u003","amount":499}],"split":{"type":"equal","users":["u001","u003","u005"]}} | D6: 0 9 5 * * | E6: 2026-05-05 09:00:00 | F6: =TRUE() -> TRUE | G6: u003

Sheet subscriptions
A1: subscriptions
A2: Pro tier subscriptions. gateway_sub_id is the Razorpay/App Store/Play Store subscription ID for webhook reconciliation.
A4: id | B4: user_id | C4: plan | D4: status | E4: started_at | F4: current_period_end | G4: gateway | H4: gateway_sub_id
A5: sub001 | B5: u005 | C5: yearly | D5: active | E5: 2026-03-01 12:00:00 | F5: 2027-03-01 12:00:00 | G5: razorpay | H5: rzp_sub_KARAN001
A6: sub002 | B6: u002 | C6: monthly | D6: trial | E6: 2026-04-20 10:00:00 | F6: 2026-05-20 10:00:00 | G6: razorpay | H6: rzp_sub_PRIYA002

Sheet ghost_invites
A1: ghost_invites
A2: When someone adds a ghost member, we generate an invite link. When the ghost user clicks it and signs up, we set claimed_by + claimed_at and merge their ghost record into a real user.
A4: id | B4: group_id | C4: ghost_user_id | D4: contact_phone | E4: contact_email | F4: link_token | G4: claimed_by | H4: claimed_at | I4: created_at
A5: gi001 | B5: g002 | C5: u006 | D5: +919812340099 | F5: tok_abc123xyz789 | I5: 2026-04-10 19:00:00

Sheet balance_summary
A1: ★ balance_summary (computed via formulas from ledger_entries)
A2: This sheet uses SUMIFS against the ledger_entries sheet to prove the model. Edit any amount in ledger_entries and these numbers update — that's the whole point of double-entry.
A4: user_id | B4: name | C4: total_owed_to_them (INR) | D4: total_they_owe (INR) | E4: net_balance (INR) | F4: interpretation
A5: u001 | B5: Aarav | C5: =SUMIFS(ledger_entries!$H$4:$H$1000,ledger_entries!$F$4:$F$1000,A5) -> 40200 | D5: =SUMIFS(ledger_entries!$H$4:$H$1000,ledger_entries!$G$4:$G$1000,A5) -> 15900 | E5: =C5-D5 -> 24300 | F5: =IF(E5>0,"is owed "&TEXT(E5,"₹#,##0"),IF(E5<0,"owes "&TEXT(-E5,"₹#,##0"),"square")) -> is owed ₹24,300
A6: u002 | B6: Priya | C6: =SUMIFS(ledger_entries!$H$4:$H$1000,ledger_entries!$F$4:$F$1000,A6) -> 3600 | D6: =SUMIFS(ledger_entries!$H$4:$H$1000,ledger_entries!$G$4:$G$1000,A6) -> 5200 | E6: =C6-D6 -> -1600 | F6: =IF(E6>0,"is owed "&TEXT(E6,"₹#,##0"),IF(E6<0,"owes "&TEXT(-E6,"₹#,##0"),"square")) -> owes ₹1,600
A7: u003 | B7: Rohan | C7: =SUMIFS(ledger_entries!$H$4:$H$1000,ledger_entries!$F$4:$F$1000,A7) -> 15000 | D7: =SUMIFS(ledger_entries!$H$4:$H$1000,ledger_entries!$G$4:$G$1000,A7) -> 20900 | E7: =C7-D7 -> -5900 | F7: =IF(E7>0,"is owed "&TEXT(E7,"₹#,##0"),IF(E7<0,"owes "&TEXT(-E7,"₹#,##0"),"square")) -> owes ₹5,900
A8: u004 | B8: Neha | C8: =SUMIFS(ledger_entries!$H$4:$H$1000,ledger_entries!$F$4:$F$1000,A8) -> 0 | D8: =SUMIFS(ledger_entries!$H$4:$H$1000,ledger_entries!$G$4:$G$1000,A8) -> 900 | E8: =C8-D8 -> -900 | F8: =IF(E8>0,"is owed "&TEXT(E8,"₹#,##0"),IF(E8<0,"owes "&TEXT(-E8,"₹#,##0"),"square")) -> owes ₹900
A9: u005 | B9: Karan | C9: =SUMIFS(ledger_entries!$H$4:$H$1000,ledger_entries!$F$4:$F$1000,A9) -> 0 | D9: =SUMIFS(ledger_entries!$H$4:$H$1000,ledger_entries!$G$4:$G$1000,A9) -> 15000 | E9: =C9-D9 -> -15000 | F9: =IF(E9>0,"is owed "&TEXT(E9,"₹#,##0"),IF(E9<0,"owes "&TEXT(-E9,"₹#,##0"),"square")) -> owes ₹15,000
A10: u006 | B10: Vikram (ghost) | C10: =SUMIFS(ledger_entries!$H$4:$H$1000,ledger_entries!$F$4:$F$1000,A10) -> 0 | D10: =SUMIFS(ledger_entries!$H$4:$H$1000,ledger_entries!$G$4:$G$1000,A10) -> 900 | E10: =C10-D10 -> -900 | F10: =IF(E10>0,"is owed "&TEXT(E10,"₹#,##0"),IF(E10<0,"owes "&TEXT(-E10,"₹#,##0"),"square")) -> owes ₹900
B12: SANITY CHECK | C12: =SUM(C5:C10) -> 58800 | D12: =SUM(D5:D10) -> 58800 | E12: =SUM(E5:E10) -> 0 | F12: Net should = 0 (every debit has a credit)

Sheet workflow_example
A1: ★ Workflow walkthrough — what happens when an expense is added & settled
A3: Step | B3: Action | C3: What happens in the DB
A4: 1 | B4: User taps "Add Expense" | C4: Mobile app opens form. Local draft kept in WatermelonDB until save.
A5: 2 | B5: User enters: ₹4500 dinner, Priya paid, split equally 5 ways including ghost Vikram | C5: No DB writes yet — all client-side.
A6: 3 | B6: User attaches receipt photo | C6: Photo uploaded to S3 → row inserted in receipts (ocr_status=pending). receipt_id returned.
A7: 4 | B7: OCR worker picks up receipt async | C7: receipts.ocr_status → done. ocr_data populated with parsed items.
A8: 5 | B8: User reviews parsed items, confirms & taps Save | C8: API receives full payload.
A9: 6 | B9: Backend opens a single Postgres transaction | C9: BEGIN;
A10: 7 | B10: Insert into expenses | C10: 1 row in expenses (e002).
A11: 8 | B11: Insert into expense_payers | C11: 1 row: (e002, u002, 4500).
A12: 9 | B12: Insert into expense_splits | C12: 5 rows: one per person, share_amount=900.
A13: 10 | B13: Insert into expense_items + assignments (because itemized) | C13: 4 items, multiple assignments.
A14: 11 | B14: Insert into ledger_entries | C14: ★ 4 rows: u002→u001, u002→u003, u002→u004, u002→u006 (each 900). All share txn_id=txn002.
... A17: 14 | B17: Outbox worker reads pending notifications | C17: Pushes FCM/APNs to all group members except sender.
B19: ── A few days later, Rohan settles up ──
A20: 15 | B20: Rohan taps "Settle Up" on his ₹15k debt to Aarav | C20: App generates UPI deep link: upi://pay?pa=aarav@oksbi&am=15000&tn=...
A21: 16 | B21: UPI app opens, Rohan confirms with PIN | C21: External — no DB writes. App returns to ours.
A22: 17 | B22: Rohan taps "Mark as paid" in our app | C22: API call to /settlements with idempotency_key.
A23: 18 | B23: Backend opens transaction | C23: BEGIN;
A24: 19 | B24: Insert into settlements (status=success) | C24: 1 row: s001, payer=u003, payee=u001, 15000, method=upi_deeplink.
A25: 20 | B25: Insert ledger reversal entry | C25: ★ 1 row: debit=u003, credit=u001, 15000, source=settlement, source_id=s001, txn_id=txn005. This CANCELS le001.
A26: 21 | B26: Insert into audit_log + notifications | C26: Aarav gets push: "Rohan paid you ₹15,000".
A27: 22 | B27: Commit | C27: COMMIT.
A28: 23 | B28: Recompute balance | C28: Open balance_summary — Rohan now shows 0 with Aarav (le001 + le010 cancel out). Karan still owes 15k.
A30: ★ | B30: KEY TAKEAWAY | C30: Balances are NEVER stored. They are SUMIFS over ledger_entries. Expenses can be edited or deleted — we just write reversal ledger entries. The ledger is append-only and is the audit trail for money.
